{
    "swagger": "2.0",
    "info": {
        "contact": {}
    },
    "paths": {
        "/GetCenterInfo/": {
            "get": {
                "description": "aaaaaa",
                "consumes": [
                    "application/x-json-stream"
                ],
                "parameters": [
                    {
                        "type": "string",
                        "description": "必須ではありません。",
                        "name": "none",
                        "in": "query"
                    }
                ],
                "responses": {
                    "200": {
                        "description": "ok",
                        "schema": {
                            "type": "string"
                        }
                    }
                }
            }
        }
    }
}